aio_yamlconfig/__init__.py
aio_yamlconfig/config.py
aio_yamlconfig/trafarets.py
aio_yamlconfig-0.2.0.dist-info/DESCRIPTION.rst
aio_yamlconfig-0.2.0.dist-info/METADATA
aio_yamlconfig-0.2.0.dist-info/RECORD
aio_yamlconfig-0.2.0.dist-info/WHEEL
aio_yamlconfig-0.2.0.dist-info/metadata.json
aio_yamlconfig-0.2.0.dist-info/top_level.txt
