Metadata-Version: 2.0
Name: aio-yamlconfig
Version: 0.2.0
Summary: YAML configuration parser with validation.
Home-page: https://github.com/rrader/aio_yamlconfig
Author: Roman Rader
Author-email: antigluk@gmail.com
License: BSD
Platform: POSIX
Classifier: License :: OSI Approved :: BSD License
Classifier: Intended Audience :: Developers
Classifier: Programming Language :: Python :: 3
Classifier: Programming Language :: Python :: 3.5
Classifier: Programming Language :: Python :: 3.6
Classifier: Environment :: Web Environment
Classifier: Development Status :: 4 - Beta
Requires-Dist: PyYAML
Requires-Dist: trafaret
